amari/__init__.py
amari/api.py
amari/cache.py
amari/exceptions.py
amari/objects.py
amari_api.py-1.3.0.dist-info/LICENSE
amari_api.py-1.3.0.dist-info/METADATA
amari_api.py-1.3.0.dist-info/WHEEL
amari_api.py-1.3.0.dist-info/top_level.txt
amari_api.py-1.3.0.dist-info/RECORD
