Metadata-Version: 2.1
Name: amari-api.py
Version: 1.3.0
Summary: An asynchronous API wrapper for the Amari API.
Home-page: https://github.com/RayyanW786/amaripy
Author: RayyanW786
License: MIT
Project-URL: Documentation, https://amari-py.readthedocs.io/en/latest/
Classifier: Development Status :: 5 - Production/Stable
Classifier: Intended Audience :: Developers
Classifier: License :: OSI Approved :: MIT License
Classifier: Programming Language :: Python :: 3.9
Classifier: Programming Language :: Python :: 3.10
Classifier: Programming Language :: Python :: 3.11
Classifier: Programming Language :: Python :: 3.12
Requires-Python: <4,>=3.9
License-File: LICENSE
Requires-Dist: aiohttp<4.0.0,>=3.7.4
